conf.py
playwright_trace_browser/__init__.py
playwright_trace_browser/__main__.py
playwright_trace_browser/_folder.py
playwright_trace_browser/_image.py
playwright_trace_browser/_viewer.py
playwright_trace_browser/app.py
playwright_trace_browser/app.tcss
version.py
playwright_trace_browser-1.1.2.dist-info/WHEEL
playwright_trace_browser-1.1.2.dist-info/LICENSE.md
playwright_trace_browser-1.1.2.dist-info/entry_points.txt
playwright_trace_browser-1.1.2.dist-info/METADATA
playwright_trace_browser-1.1.2.dist-info/RECORD
