Metadata-Version: 2.1
Name: playwright-trace-browser
Version: 1.1.2
Summary: A TUI app for exploring Playwright traces
License: MIT
Author: Nick DeRobertis
Author-email: derobertis.nick@gmail.com
Requires-Python: >=3.9,<4.0
Classifier: Development Status :: 3 - Alpha
Classifier: Intended Audience :: Developers
Classifier: License :: OSI Approved :: MIT License
Classifier: Programming Language :: Python :: 3
Classifier: Programming Language :: Python :: 3.9
Classifier: Programming Language :: Python :: 3.10
Classifier: Programming Language :: Python :: 3.11
Classifier: Programming Language :: Python :: 3.10
Classifier: Programming Language :: Python :: 3.11
Classifier: Programming Language :: Python :: 3.7
Classifier: Programming Language :: Python :: 3.8
Classifier: Programming Language :: Python :: 3.9
Requires-Dist: more-itertools (>=10.2.0,<11.0.0)
Requires-Dist: playwright (>=1.43.0)
Requires-Dist: textual (>=0.48.1,<0.49.0)
Project-URL: documentation, https://nickderobertis.github.io/playwright-trace-browser
Project-URL: repository, https://github.com/nickderobertis/playwright-trace-browser
